{

"GxObject":{"ObjectType":"BusinessComponent","Name":"Wwpbaseobjects.SecFunctionality","idConnectivitySupport":"idInherit","Structure":{"Levels":[{"Name":"Secfunctionality","ParentLevel":"","LevelName":"WWPBaseObjects.SecFunctionality","Description":"权限","Attributes":[{"Name":"SecFunctionalityId","Caption":"功能编号","default":"0","AutoNumber":"true","IsKey":"true","ReadOnly":"false","AttributeType":"int","Description":"功能编号","Length":"10","Decimals":"0","Signed":"false","AllowDBNulls":"false","InternalName":"SecFunctionalityId","InputPicture":"ZZZZZZZZZ9","Type":"xs:int"},{"Name":"SecFunctionalityKey","Caption":"权限名称","default":"","IsKey":"false","ReadOnly":"false","AttributeType":"svchar","Description":"权限名称","Length":"100","Decimals":"0","Signed":"false","AllowDBNulls":"false","InternalName":"SecFunctionalityKey","InputPicture":"","Type":"xs:string"},{"Name":"SecFunctionalityDescription","Caption":"权限描述","default":"","IsKey":"false","ReadOnly":"false","AttributeType":"svchar","Description":"权限描述","Length":"100","Decimals":"0","Signed":"false","AllowDBNulls":"false","InternalName":"SecFunctionalityDescription","DescriptionAtt":"true","InputPicture":"","Type":"xs:string"},{"Name":"SecFunctionalityType","Caption":"权限类型","default":"0","IsKey":"false","ReadOnly":"true","AttributeType":"int","Description":"权限类型","Length":"2","Decimals":"0","Signed":"false","AllowDBNulls":"false","Domain":"WWPSecFunctionalityTypes","InternalName":"SecFunctionalityType","InputPicture":"Z9","Type":"xs:int"},{"Name":"SecParentFunctionalityId","Caption":"父功能编号","default":"0","SuperType":"SecFunctionalityId","SubtypeGroup":"SecFunctionalityFunctionality","IsKey":"false","ReadOnly":"false","AttributeType":"int","Description":"父功能编号","Length":"10","Decimals":"0","Signed":"false","AllowDBNulls":"true","InternalName":"SecParentFunctionalityId","InputPicture":"ZZZZZZZZZ9","Type":"xs:int"},{"Name":"SecParentFunctionalityDescription","Caption":"父功能","default":"","SuperType":"SecFunctionalityDescription","SubtypeGroup":"SecFunctionalityFunctionality","IsKey":"false","ReadOnly":"true","AttributeType":"svchar","Description":"父功能","Length":"100","Decimals":"0","Signed":"false","AllowDBNulls":"true","InternalName":"SecParentFunctionalityDescription","InputPicture":"","Type":"xs:string"},{"Name":"SecFunctionalityActive","Caption":"权限是否启用？","default":"","IsKey":"false","ReadOnly":"false","AttributeType":"boolean","Description":"权限是否启用？","Length":"4","Decimals":"0","Signed":"false","AllowDBNulls":"false","InternalName":"SecFunctionalityActive","InputPicture":"","Type":"xs:string"}]}]},"Relations":{"ManyToOne":{"references":[{"Name":"Wwpbaseobjects\\SecFunctionalitySecParentFunctionalityId","BusinessComponent":"Wwpbaseobjects\\SecFunctionality","LevelName":"WWPBaseObjects.SecFunctionality","Description":"权限","ForeignKey":{"KeyAttributes":[{"Name":"SecParentFunctionalityId","Type":"int","AtributeSuperType":"SecFunctionalityId"}]},"InferredAttributes":{"Attributes":[{"Name":"SecParentFunctionalityDescription","Type":"svchar","AtributeSuperType":"SecFunctionalityDescription"}]}}]}}}
}
